webbot/__init__.py
webbot/webbot.py
webbot/drivers/chrome_linux
webbot/drivers/chrome_mac
webbot/drivers/chrome_windows.exe
webbot-0.34.dist-info/LICENSE
webbot-0.34.dist-info/METADATA
webbot-0.34.dist-info/WHEEL
webbot-0.34.dist-info/top_level.txt
webbot-0.34.dist-info/RECORD
