Metadata-Version: 1.1
Name: webbot
Version: 0.34
Summary: Web Browser automation and testing library for python with more features and simpler api than selenium
Home-page: https://github.com/nateshmbhat/webbot
Author: Natesh M Bhat
Author-email: nateshmbhatofficial@gmail.com
License: UNKNOWN
Keywords: webbot,selenium,autoweb,automate,automation,pyttsx3,bs4,beautiful soup,web,autoweb,auto,pyauto,pyautogui
Platform: UNKNOWN
Classifier: Environment :: Console
Classifier: Intended Audience :: End Users/Desktop
Classifier: Intended Audience :: Developers
Classifier: Intended Audience :: Information Technology
Classifier: Intended Audience :: System Administrators
Classifier: Operating System :: MacOS :: MacOS X
Classifier: Operating System :: Microsoft :: Windows
Classifier: Operating System :: POSIX
Classifier: License :: OSI Approved :: MIT License
Classifier: Programming Language :: Python :: 3
Classifier: Programming Language :: Python :: 3.5
Classifier: Programming Language :: Python :: 3.6
Classifier: Programming Language :: Python :: 3.7
